Metadata-Version: 2.1
Name: sentry-cronjob-monitoring-johanalmquist
Version: 0.0.3
Summary: A package for use Sentrys Cronjob Monitor Module
Home-page: https://github.com/johanalmquist/sentry_cronjob_monitoring
Author: Johan Almquist
Author-email: Johan Almquist <johan.almquist@aranya.se>
Project-URL: Homepage, https://github.com/johanalmquist/sentry_cronjob_monitoring
Project-URL: Bug Tracker, https://github.com/johanalmquist/sentry_cronjob_monitoring/issues
Classifier: Programming Language :: Python :: 3
Classifier: License :: OSI Approved :: MIT License
Classifier: Operating System :: OS Independent
Requires-Python: >=3.8
License-File: LICENSE
Requires-Dist: httpx
